{"is_source_file": false, "format": "", "description": "", "external_files": [], "external_methods": [], "published": [], "classes": [], "methods": [], "calls": [], "search-terms": [], "state": 2, "file_id": 8, "knowledge_revision": 46, "git_revision": "17009d6271ffc17fc1f7021c7c24eecf1055c3c0", "revision_history": [{"21": "8f9904843f6bbcc272c92ea86dd7cd4bd81a63ee"}, {"46": "17009d6271ffc17fc1f7021c7c24eecf1055c3c0"}], "ctags": [], "hash": "9e61fe8dda48c78d6063ea575812f732", "format-version": 4, "code-base-name": "notes_backend", "filename": "notes_backend/api/__init__.py"}